LICENSE
MANIFEST.in
README.md
requirements.txt
setup.py
Django_Pizza.egg-info/PKG-INFO
Django_Pizza.egg-info/SOURCES.txt
Django_Pizza.egg-info/dependency_links.txt
Django_Pizza.egg-info/requires.txt
Django_Pizza.egg-info/top_level.txt
pizza/__init__.py
pizza/middleware.py
pizza/utils.py
pizza/blog/__init__.py
pizza/blog/admin.py
pizza/blog/models.py
pizza/blog/tests.py
pizza/blog/urls.py
pizza/blog/urls_blogs.py
pizza/blog/urls_podcast.py
pizza/blog/views.py
pizza/blog/migrations/0001_initial.py
pizza/blog/migrations/0002_auto.py
pizza/blog/migrations/0003_auto__add_field_blog_image.py
pizza/blog/migrations/0004_auto__add_field_mediafile_duration.py
pizza/blog/migrations/0005_auto__add_field_fileformat_mtype.py
pizza/blog/migrations/0006_auto__add_field_post_audio_embed__add_field_post_video_embed.py
pizza/blog/migrations/__init__.py
pizza/blog/templates/pizza/blog/index.atom.xml
pizza/blog/templates/pizza/blog/index.rss.xml
pizza/blog/templates/pizza/blog/itunes.xml
pizza/blog/templatetags/__init__.py
pizza/blog/templatetags/pizza_blog.py
pizza/calendar/__init__.py
pizza/calendar/admin.py
pizza/calendar/models.py
pizza/calendar/urls.py
pizza/calendar/views.py
pizza/calendar/migrations/0001_initial.py
pizza/calendar/migrations/0002_auto__add_field_event_url.py
pizza/calendar/migrations/__init__.py
pizza/kitchen_sink/__init__.py
pizza/kitchen_sink/admin.py
pizza/kitchen_sink/models.py
pizza/kitchen_sink/tests.py
pizza/kitchen_sink/urls.py
pizza/kitchen_sink/views.py
pizza/kitchen_sink/widgets.py
pizza/kitchen_sink/management/__init__.py
pizza/kitchen_sink/management/commands/__init__.py
pizza/kitchen_sink/management/commands/importpages.py
pizza/kitchen_sink/migrations/0001_initial.py
pizza/kitchen_sink/migrations/0002_auto__add_inline.py
pizza/kitchen_sink/migrations/0003_auto__add_field_inline_icnt.py
pizza/kitchen_sink/migrations/__init__.py
pizza/kitchen_sink/static/ks/ckeditor/CHANGES.md
pizza/kitchen_sink/static/ks/ckeditor/LICENSE.md
pizza/kitchen_sink/static/ks/ckeditor/README.md
pizza/kitchen_sink/static/ks/ckeditor/build-config.js
pizza/kitchen_sink/static/ks/ckeditor/ckeditor.js
pizza/kitchen_sink/static/ks/ckeditor/config.js
