Metadata-Version: 1.1
Name: Django-Pizza
Version: 14.04.2
Summary: Yet another Django CMS.
Home-page: https://github.com/pizzapanther/Django-Pizza
Author: Paul Bailey
Author-email: paul.m.bailey@gmail.com
License: BSD
Platform: UNKNOWN
Classifier: Development Status :: 5 - Production/Stable
Classifier: Environment :: Web Environment
Classifier: Framework :: Django
Classifier: Intended Audience :: Developers
Classifier: License :: OSI Approved :: BSD License
Classifier: Operating System :: OS Independent
Classifier: Programming Language :: Python
